{
  "header": [
    "slug",
    "name",
    "date",
    "solved",
    "total",
    "problems",
    "link",
    "tags"
  ],
  "rows": [
    {
      "slug": "2026-the-2019-polish-collegiate-programming-contest-amppz-2019",
      "name": "The 2019 Polish Collegiate Programming Contest (AMPPZ 2019)",
      "date": "2026.06.15",
      "solved": 6,
      "total": 12,
      "problems": "O;.;O;O;.;O;.;O;Ø;.;.;.",
      "link": "https://qoj.ac/contest/559",
      "tags": ""
    },
    {
      "slug": "2026-shandong-provincial-collegiate-programming-contest",
      "name": "2026 年山东省大学生程序设计竞赛",
      "date": "2026.05.25",
      "solved": 10,
      "total": 13,
      "problems": "O;.;O;Ø;O;.;O;Ø;O;Ø;O;O;.",
      "link": "https://qoj.ac/contest/3767",
      "tags": ""
    }
  ]
}